logmole/__init__.py
logmole/containers.py
logmole/types.py
logmole/utilities.py
logmole-0.9.1.dist-info/LICENSE.md
logmole-0.9.1.dist-info/METADATA
logmole-0.9.1.dist-info/WHEEL
logmole-0.9.1.dist-info/top_level.txt
logmole-0.9.1.dist-info/RECORD
