Metadata-Version: 2.1
Name: logmole
Version: 0.9.1
Summary: An Extendable and Versatile Logparsing System
Home-page: https://github.com/rkoschmitzky/logmole
Author: Rico Koschmitzky
Author-email: contact@ricokoschmitzky.com
License: MIT
Platform: UNKNOWN
Classifier: Development Status :: 4 - Beta
Classifier: Intended Audience :: Developers
Classifier: Intended Audience :: System Administrators
Classifier: License :: OSI Approved :: MIT License
Classifier: Programming Language :: Python
Classifier: Programming Language :: Python :: 2
Classifier: Programming Language :: Python :: 2.6
Classifier: Programming Language :: Python :: 2.7
Classifier: Programming Language :: Python :: 3
Classifier: Programming Language :: Python :: 3.7
Classifier: Programming Language :: Python :: 3.8
Classifier: Topic :: Software Development :: Libraries :: Python Modules
Classifier: Topic :: Utilities
Classifier: Topic :: System :: Logging
Classifier: Topic :: System :: Monitoring
Classifier: Topic :: Text Processing :: Filters
